ffquant/__init__.py
ffquant/analyzers/OrderAnalyzer.py
ffquant/analyzers/Returns.py
ffquant/analyzers/SharpeRatio.py
ffquant/analyzers/__init__.py
ffquant/brokers/MyBackBroker.py
ffquant/brokers/MyBackBrokerCombo.py
ffquant/brokers/MyBroker.py
ffquant/brokers/MyBrokerCombo.py
ffquant/brokers/TradingView.py
ffquant/brokers/__init__.py
ffquant/calendar/MyCalendar.py
ffquant/calendar/__init__.py
ffquant/feeds/FakeFeed.py
ffquant/feeds/Line.py
ffquant/feeds/MyFeed.py
ffquant/feeds/MyLiveFeed.py
ffquant/feeds/__init__.py
ffquant/indicators/ActBuySellHedgePos.py
ffquant/indicators/ActiveBuySell.py
ffquant/indicators/AggSignalV3.py
ffquant/indicators/BaseIndicator.py
ffquant/indicators/BondVolume.py
ffquant/indicators/CnTrsAbs.py
ffquant/indicators/Fluctuation.py
ffquant/indicators/HedgedPosition.py
ffquant/indicators/HkTrsAbs.py
ffquant/indicators/HsiCzLv.py
ffquant/indicators/IndexListIndicator.py
ffquant/indicators/LongTermDirection.py
ffquant/indicators/OpenUStock.py
ffquant/indicators/OpenUWarrant.py
ffquant/indicators/PnlPattern.py
ffquant/indicators/PriceActionDescriptor.py
ffquant/indicators/PriceMoving.py
ffquant/indicators/PricePattern.py
ffquant/indicators/PriceTrendDescribe.py
ffquant/indicators/ProdBuySellSeqZyj.py
ffquant/indicators/Shift.py
ffquant/indicators/ShortTermDirection.py
ffquant/indicators/StopOpenPos.py
ffquant/indicators/ThvAdjust.py
ffquant/indicators/TradeAction.py
ffquant/indicators/Trend.py
ffquant/indicators/TrendCz.py
ffquant/indicators/TrendHold.py
ffquant/indicators/TrendHoldAdjust.py
ffquant/indicators/TrendHoldAdv.py
ffquant/indicators/TrendHoldFast.py
ffquant/indicators/TrendOscillate.py
ffquant/indicators/TrendPosFc.py
ffquant/indicators/TrendPredict.py
ffquant/indicators/TrendSector.py
ffquant/indicators/TrendWarrant.py
ffquant/indicators/TurningPoint.py
ffquant/indicators/TurningPointWarrant.py
ffquant/indicators/VolStrengthBOND.py
ffquant/indicators/VolStrengthCNHHKD.py
ffquant/indicators/VolStrengthHKStock.py
ffquant-4.0.6.dist-info/licenses/LICENSE
ffquant-4.0.6.dist-info/METADATA
ffquant-4.0.6.dist-info/WHEEL
ffquant-4.0.6.dist-info/top_level.txt
ffquant-4.0.6.dist-info/RECORD
