Metadata-Version: 2.4
Name: ffquant
Version: 4.0.6
Summary: A python package for providing fintech indicators
Home-page: https://github.com/lihuapinghust/ffquant
Author: Jonathan Lee
Author-email: lihuapinghust@gmail.com
Classifier: Programming Language :: Python :: 3
Classifier: License :: OSI Approved :: MIT License
Classifier: Operating System :: OS Independent
Requires-Python: >=3.6
License-File: LICENSE
Requires-Dist: backtrader==1.9.78.123
Requires-Dist: matplotlib==3.9.2
Dynamic: author
Dynamic: author-email
Dynamic: classifier
Dynamic: description
Dynamic: description-content-type
Dynamic: home-page
Dynamic: license-file
Dynamic: requires-dist
Dynamic: requires-python
Dynamic: summary
